[
  {
    "name": "pergi pagi pulang pagi",
    "url": "http://d.top4top.io/m_3356r7u6g1.mp3"
  },
  {
    "name": "the lazy song",
    "url": "http://e.top4top.io/m_3353cxoxl1.mp3"
  },
  {
    "name": "romantic homicide",
    "url": "http://g.top4top.io/m_3363oucnx1.mp3"
  },
  {
    "name": "every breath you take",
    "url": "http://j.top4top.io/m_3362zysje2.mp3"
  },
  {
    "name": "dj kampang",
    "url": "http://d.top4top.io/m_3382w5e140.mp3"
  },
  {
    "name": "stecu stecu",
    "url": "http://d.top4top.io/m_3382kw56r0.mp3"
  },
  {
    "name": "slank top songs",
    "url": "http://l.top4top.io/m_33825x5o11.mp3"
  },
  {
    "name": "tomskate top song",
    "url": "http://l.top4top.io/m_3203reahm1.mp3"
  },
  {
    "name": "serana",
    "url": "http://c.top4top.io/m_3189g559o1.mp3"
  },
  {
    "name": "baon cikadap halal",
    "url": "http://f.top4top.io/m_3191anso41.mp3"
  },
  {
    "name": "untungnya rap",
    "url": "http://f.top4top.io/m_3178r1yvf0.mp3"
  },
  {
    "name": "dreams tonite",
    "url": "http://e.top4top.io/m_32029kdz21.mp3"
  },
  {
    "name": "dark red",
    "url": "http://b.top4top.io/m_32234k7qh1.mp3"
  },
  {
    "name": "when the sun hits",
    "url": "http://c.top4top.io/m_3223s73ms1.mp3"
  },
  {
    "name": "the american dawn her",
    "url": "http://d.top4top.io/m_32232odpu1.mp3"
  },
  {
    "name": "shake it off",
    "url": "http://e.top4top.io/m_3223l4t4z1.mp3"
  },
  {
    "name": "feels",
    "url": "http://f.top4top.io/m_3223kpppg2.mp3"
  },
  {
    "name": "sign of the times",
    "url": "http://g.top4top.io/m_3223iueqz3.mp3"
  },
  {
    "name": "feels so close",
    "url": "http://h.top4top.io/m_3223rylvy4.mp3"
  },
  {
    "name": "vampire heart",
    "url": "http://i.top4top.io/m_32230sqhp5.mp3"
  },
  {
    "name": "six days",
    "url": "http://j.top4top.io/m_3223zjdgj6.mp3"
  },
  {
    "name": "rich baby daddy",
    "url": "http://k.top4top.io/m_3223o1ivl7.mp3"
  },
  {
    "name": "boom boom boom boom",
    "url": "http://l.top4top.io/m_3223uekx38.mp3"
  },
  {
    "name": "chlorine",
    "url": "http://a.top4top.io/m_32230sve19.mp3"
  },
  {
    "name": "rockstar",
    "url": "http://b.top4top.io/m_3223nuq7v10.mp3"
  },
  {
    "name": "mind games",
    "url": "http://f.top4top.io/m_32252si4l1.mp3"
  },
  {
    "name": "All Girls Are The Same",
    "url": "http://d.top4top.io/m_3225z7i151.mp3"
  },
  {
    "name": "yad",
    "url": "http://e.top4top.io/m_3147h6n9k0.mp3"
  },
  {
    "name": "pergilah kau",
    "url": "http://b.top4top.io/m_3186yst8t4.mp3"
  },
  {
    "name": "naff full album",
    "url": "http://d.top4top.io/m_3186eyqaf6.mp3"
  },
  {
    "name": "arti kehidupan",
    "url": "http://f.top4top.io/m_32398yeyf1.mp3"
  },
  {
    "name": "love me",
    "url": "http://l.top4top.io/m_32448m5mm1.mp3"
  },
  {
    "name": "tumblr girls",
    "url": "http://a.top4top.io/m_3244bhqwh2.mp3"
  },
  {
    "name": "a took a pill in ibiza",
    "url": "http://f.top4top.io/m_3244nx29o1.mp3"
  },
  {
    "name": "where you go",
    "url": "http://b.top4top.io/m_3244tcfwq1.mp3"
  },
  {
    "name": "no one can stop us",
    "url": "http://h.top4top.io/m_3244ezxie1.mp3"
  },
  {
    "name": "hope",
    "url": "http://f.top4top.io/m_32441p2hh1.mp3"
  },
  {
    "name": "band for band",
    "url": "http://k.top4top.io/m_3244pb4yi1.mp3"
  },
  {
    "name": "tahooooo",
    "url": "http://l.top4top.io/m_3245gimm41.mp3"
  },
  {
    "name": "fix you",
    "url": "http://c.top4top.io/m_3247lrxp81.mp3"
  },
  {
    "name": "apocalypse",
    "url": "http://d.top4top.io/m_32476l0pv1.mp3"
  },
  {
    "name": "smack that",
    "url": "http://f.top4top.io/m_3249hbks51.mp3"
  },
  {
    "name": "sadrah",
    "url": "http://b.top4top.io/m_3249bwwvn1.mp3"
  },
  {
    "name": "nuts",
    "url": "http://h.top4top.io/m_32555ht3t1.mp3"
  },
  {
    "name": "yeah yeah yeahs maps",
    "url": "http://k.top4top.io/m_3267gy83p1.mp3"
  },
  {
    "name": "penyangkalan",
    "url": "http://h.top4top.io/m_32754qhyc1.mp3"
  },
  {
    "name": "i feel it coming",
    "url": "http://d.top4top.io/m_3294i77ic1.mp3"
  },
  {
    "name": "garam dan madu",
    "url": "http://k.top4top.io/m_3289sv1js0.mp3"
  },
  {
    "name": "tiga tiga x",
    "url": "http://b.top4top.io/m_3318ezpku1.mp3"
  },
  {
    "name": "neneku pahlawanku",
    "url": "http://f.top4top.io/m_3353bu89s1.mp3"
  },
  {
    "name": "yank",
    "url": "http://b.top4top.io/m_3354kx2t91.mp3"
  },
  {
    "name": "ginseng strip",
    "url": "http://b.top4top.io/m_3360ae9bx1.mp3"
  },
  {
    "name": "baby im back",
    "url": "http://a.top4top.io/m_3360li1qh1.mp3"
  },
  {
    "name": "gods plan",
    "url": "http://h.top4top.io/m_336081qsf1.mp3"
  },
  {
    "name": "feel it",
    "url": "http://k.top4top.io/m_3361hxesz1.mp3"
  },
  {
    "name": "love hurts",
    "url": "http://i.top4top.io/m_336234oh61.mp3"
  },
  {
    "name": "SEGENAP CINTA YANG ADA",
    "url": "http://l.top4top.io/m_3334hvz9m0.mp3"
  },
  {
    "name": "CINTA UNTUK STARLA",
    "url": "http://j.top4top.io/m_3334vhly70.mp3"
  },
  {
    "name": "SATRIA TANPA PEDANG",
    "url": "http://g.top4top.io/m_3325seqne0.mp3"
  },
  {
    "name": "GARAM CINA",
    "url": "http://h.top4top.io/m_3321e938m0.mp3"
  },
  {
    "name": "HBD",
    "url": "http://j.top4top.io/m_3319oyuc90.mp3"
  },
  {
    "name": "MOSHING",
    "url": "http://d.top4top.io/m_3319manax1.mp3"
  },
  {
    "name": "YOMAN",
    "url": "http://l.top4top.io/m_33164d0mu0.mp3"
  },
  {
    "name": "KAMU DAN KENANGAN",
    "url": "http://f.top4top.io/m_3319luplu1.mp3"
  },
  {
    "name": "TWIKARMA",
    "url": "http://j.top4top.io/m_33632cwjn0.mp3"
  },
  {
    "name": "BAYAR POLISI BAYAR POLISI",
    "url": "http://f.top4top.io/m_3363w3q2b0.mp3"
  },
  {
    "name": "AKU YANG MALANG",
    "url": "http://a.top4top.io/m_3367xaq3f0.mp3"
  },
  {
    "name": "TAFSIR MISTIK",
    "url": "http://k.top4top.io/m_3362yfoqb0.mp3"
  },
  {
    "name": "MY HEART",
    "url": "http://c.top4top.io/m_3360gy3d60.mp3"
  },
  {
    "name": "dj phone call",
    "url": "http://d.top4top.io/m_264247pww0.mp3"
  },
  {
    "name": "right now",
    "url": "http://c.top4top.io/m_2553b59tm0.mp3"
  },
  {
    "name": "another love",
    "url": "http://k.top4top.io/m_25532h3c40.mp3"
  },
  {
    "name": "sempurna",
    "url": "http://a.top4top.io/m_25538x4im0.mp3"
  },
  {
    "name": "take me home",
    "url": "http://l.top4top.io/m_2553m9act0.mp3"
  },
  {
    "name": "mary on a cross",
    "url": "http://f.top4top.io/m_25433rqf71.mp3"
  },
  {
    "name": "duka x serana",
    "url": "http://k.top4top.io/m_2558zlrn20.mp3"
  },
  {
    "name": "strong",
    "url": "http://l.top4top.io/m_25580qw261.mp3"
  },
  {
    "name": "snowfall one hour",
    "url": "http://i.top4top.io/m_2558p9dng0.mp3"
  },
  {
    "name": "melting",
    "url": "http://j.top4top.io/m_2558dwgxj0.mp3"
  },
  {
    "name": "tak ingin usai",
    "url": "http://b.top4top.io/m_2558p1m2k0.mp3"
  },
  {
    "name": "resah jadi luka",
    "url": "http://g.top4top.io/m_2558651wn0.mp3"
  },
  {
    "name": "el pedron x mashup",
    "url": "http://i.top4top.io/m_2558jx5rz0.mp3"
  },
  {
    "name": "Cintamu ta sepahit topi miring",
    "url": "http://b.top4top.io/m_2568qcd230.mp3"
  },
  {
    "name": "see you again",
    "url": "http://j.top4top.io/m_2656dc4xl0.mp3"
  },
  {
    "name": "perfect",
    "url": "http://a.top4top.io/m_2656qvxeo0.mp3"
  },
  {
    "name": "lupakan aku kembali padanya",
    "url": "http://k.top4top.io/m_2657pne2c0.mp3"
  },
  {
    "name": "putuskan pacarmu itu",
    "url": "http://i.top4top.io/m_2657suvz80.mp3"
  },
  {
    "name": "play date",
    "url": "http://i.top4top.io/m_2588gqv4f0.mp3"
  },
  {
    "name": "memories",
    "url": "http://j.top4top.io/m_2588r6t701.mp3"
  },
  {
    "name": "eight letters",
    "url": "http://k.top4top.io/m_2588cw1xs2.mp3"
  },
  {
    "name": "treat you better",
    "url": "http://l.top4top.io/m_25880mx533.mp3"
  },
  {
    "name": "take me home",
    "url": "http://a.top4top.io/m_2588a5qli4.mp3"
  },
  {
    "name": "heat waves",
    "url": "http://c.top4top.io/m_2588t4l276.mp3"
  },
  {
    "name": "past live",
    "url": "http://d.top4top.io/m_2588imkjm7.mp3"
  },
  {
    "name": "wish you were here",
    "url": "http://e.top4top.io/m_2588zvyvw8.mp3"
  },
  {
    "name": "write the stars",
    "url": "http://f.top4top.io/m_25887dont9.mp3"
  },
  {
    "name": "love story",
    "url": "http://e.top4top.io/m_25888y2yr1.mp3"
  },
  {
    "name": "night changes",
    "url": "http://f.top4top.io/m_2588v69og2.mp3"
  },
  {
    "name": "before you go",
    "url": "http://g.top4top.io/m_2588rhxgj3.mp3"
  },
  {
    "name": "ghost",
    "url": "http://h.top4top.io/m_258857f0r4.mp3"
  },
  {
    "name": "bad liar",
    "url": "http://i.top4top.io/m_2588jnsib5.mp3"
  },
  {
    "name": "alone",
    "url": "http://j.top4top.io/m_2588fsi7h6.mp3"
  },
  {
    "name": "angels like you",
    "url": "http://h.top4top.io/m_2641fbbhg0.mp3"
  },
  {
    "name": "say yes to heaven",
    "url": "http://i.top4top.io/m_2641iq6tv1.mp3"
  },
  {
    "name": "somewhere only we know",
    "url": "http://j.top4top.io/m_26410ftz12.mp3"
  },
  {
    "name": "dandelions",
    "url": "http://c.top4top.io/m_2558jtk6k0.mp3"
  },
  {
    "name": "as it was",
    "url": "http://i.top4top.io/m_2601q83yb0.mp3"
  },
  {
    "name": "atlantis",
    "url": "http://e.top4top.io/m_2601hp5r10.mp3"
  },
  {
    "name": "laskar pelangi",
    "url": "http://g.top4top.io/m_2569qyxux0.mp3"
  },
  {
    "name": "night changes",
    "url": "http://j.top4top.io/m_256931bp20.mp3"
  },
  {
    "name": "under the influence",
    "url": "http://a.top4top.io/m_2498nsszz0.mp3"
  },
  {
    "name": "doin time",
    "url": "http://c.top4top.io/m_2498jpfju2.mp3"
  },
  {
    "name": "dj cintamu itu hoax",
    "url": "http://l.top4top.io/m_2498rwol52.mp3"
  },
  {
    "name": "dancing with your ghost",
    "url": "http://f.top4top.io/m_2500280kw0.mp3"
  },
  {
    "name": "dj devil inside me",
    "url": "http://j.top4top.io/m_25019tvrj0.mp3"
  },
  {
    "name": "dj florida low low",
    "url": "http://l.top4top.io/m_2501ux4zx2.mp3"
  },
  {
    "name": "double take",
    "url": "http://k.top4top.io/m_25257u9lp0.mp3"
  },
  {
    "name": "dj aku meriang",
    "url": "http://j.top4top.io/m_2535de2zp0.mp3"
  },
  {
    "name": "story of my life",
    "url": "http://e.top4top.io/m_2563aevwr0.mp3"
  },
  {
    "name": "ajimat my gang",
    "url": "http://e.top4top.io/m_25634iq320.mp3"
  },
  {
    "name": "trickster anthem",
    "url": "http://d.top4top.io/m_2563jcuix0.mp3"
  },
  {
    "name": "bmc kota kita",
    "url": "http://g.top4top.io/m_2563t7xu40.mp3"
  },
  {
    "name": "king of the street",
    "url": "http://i.top4top.io/m_2563fknuw0.mp3"
  },
  {
    "name": "lil tatang arivena",
    "url": "http://l.top4top.io/m_2581k5iyv0.mp3"
  },
  {
    "name": "lil tatang patriot mifr",
    "url": "http://e.top4top.io/m_2580qzwod0.mp3"
  },
  {
    "name": "lil tatang patriot",
    "url": "http://a.top4top.io/m_2581djq080.mp3"
  },
  {
    "name": "Rasah Bali",
    "url": "http://i.top4top.io/m_2635ybbod0.mp3"
  },
  {
    "name": "Phedot janji",
    "url": "http://i.top4top.io/m_2635efnxh0.mp3"
  },
  {
    "name": "Samudra",
    "url": "http://j.top4top.io/m_2635y1jfj0.mp3"
  },
  {
    "name": "Anarki",
    "url": "http://h.top4top.io/m_2635aelkx0.mp3"
  },
  {
    "name": "Melukis",
    "url": "http://h.top4top.io/m_2636owe070.mp3"
  },
  {
    "name": "Tumpah susu",
    "url": "http://j.top4top.io/m_2636nk1h90.mp3"
  },
  {
    "name": "Fly",
    "url": "http://i.top4top.io/m_2637wu6ij0.mp3"
  },
  {
    "name": "Tulus",
    "url": "http://d.top4top.io/m_26370a3gl0.mp3"
  },
  {
    "name": "Not you",
    "url": "http://j.top4top.io/m_26786x7fq0.mp3"
  },
  {
    "name": "Nemen",
    "url": "http://i.top4top.io/m_267860wo50.mp3"
  },
  {
    "name": "Bad Habit",
    "url": "http://b.top4top.io/m_2566zzpts0.mp3"
  },
  {
    "name": "Resah Jadi Luka",
    "url": "http://c.top4top.io/m_2559agaw70.mp3"
  },
  {
    "name": "Duka",
    "url": "http://i.top4top.io/m_2559k6ipw0.mp3"
  },
  {
    "name": "Sempurna",
    "url": "http://a.top4top.io/m_25538x4im0.mp3"
  },
  {
    "name": "Strong",
    "url": "http://j.top4top.io/m_2562wzad60.mp3"
  },
  {
    "name": "Until I Found You",
    "url": "http://f.top4top.io/m_2562mmjh10.mp3"
  },
  {
    "name": "Right Now speedup",
    "url": "http://k.top4top.io/m_2563410f91.mp3"
  },
  {
    "name": "Takut Tambah Dewasa",
    "url": "http://a.top4top.io/m_2563y13qj0.mp3"
  },
  {
    "name": "Dj Dalinda",
    "url": "http://h.top4top.io/m_2499ciu190.mp3"
  },
  {
    "name": "L Hal",
    "url": "http://k.top4top.io/m_2566gy4fh0.mp3"
  },
  {
    "name": "Lonely",
    "url": "http://b.top4top.io/m_2567k0twk0.mp3"
  },
  {
    "name": "Heyek Crew Suwung",
    "url": "http://c.top4top.io/m_25671hko70.mp3"
  },
  {
    "name": "Bojo Galak",
    "url": "http://f.top4top.io/m_25695zdfe0.mp3"
  },
  {
    "name": "Take Me Home",
    "url": "http://a.top4top.io/m_26013d6730.mp3"
  },
  {
    "name": "See You Again",
    "url": "http://i.top4top.io/m_2601dg93o0.mp3"
  },
  {
    "name": "Atlantis",
    "url": "http://e.top4top.io/m_2601hp5r10.mp3"
  },
  {
    "name": "SNAP",
    "url": "http://g.top4top.io/m_2601oi9aa0.mp3"
  },
  {
    "name": "Proom Queen",
    "url": "http://d.top4top.io/m_2601vds8j0.mp3"
  },
  {
    "name": "December",
    "url": "http://j.top4top.io/m_2601twj6s0.mp3"
  },
  {
    "name": "Right Now",
    "url": "http://i.top4top.io/m_2601q83yb0.mp3"
  },
  {
    "name": "Hindia Evaluasi",
    "url": "http://g.top4top.io/m_2601084lx0.mp3"
  },
  {
    "name": "Seandainya",
    "url": "http://g.top4top.io/m_2603nwiqz0.mp3"
  },
  {
    "name": "As It Was",
    "url": "http://k.top4top.io/m_2603mzl900.mp3"
  },
  {
    "name": "The Side Of Paradise",
    "url": "http://g.top4top.io/m_2603vzgb30.mp3"
  },
  {
    "name": "Limbo Sped Up",
    "url": "http://h.top4top.io/m_2603dzpg80.mp3"
  },
  {
    "name": "Money Rain",
    "url": "http://e.top4top.io/m_2603glnr80.mp3"
  },
  {
    "name": "After Dark",
    "url": "http://i.top4top.io/m_26030xike0.mp3"
  },
  {
    "name": "MIDNIGHT",
    "url": "http://f.top4top.io/m_2603d9l8k0.mp3"
  },
  {
    "name": "Somewhere Only We Know",
    "url": "http://e.top4top.io/m_2603i6lw10.mp3"
  },
  {
    "name": "You Know How We Do It",
    "url": "http://top4top.io/m_2603vhlsz0.mp3"
  },
  {
    "name": "Cha Cha",
    "url": "http://b.top4top.io/m_26030fjn10.mp3"
  },
  {
    "name": "All Alone",
    "url": "http://d.top4top.io/m_2603tf1c00.mp3"
  },
  {
    "name": "WTH",
    "url": "http://a.top4top.io/m_2603ta2x80.mp3"
  },
  {
    "name": "Jogja Istimewa",
    "url": "http://l.top4top.io/m_2603ikqcx0.mp3"
  },
  {
    "name": "Hujan kemarin",
    "url": "http://b.top4top.io/m_2625f4ghk0.mp3"
  },
  {
    "name": "Karna su sayang",
    "url": "http://h.top4top.io/m_26251ib060.mp3"
  },
  {
    "name": "JKT Seventeen",
    "url": "http://h.top4top.io/m_2673zke990.mp3"
  },
  {
    "name": "JKT Birth",
    "url": "http://f.top4top.io/m_2673euycw0.mp3"
  },
  {
    "name": "JKT Aitakatta",
    "url": "http://l.top4top.io/m_2673eoq8s0.mp3"
  },
  {
    "name": "JKT After Rain",
    "url": "http://a.top4top.io/m_2674tfdd50.mp3"
  },
  {
    "name": "JKT Bersepeda Berdua",
    "url": "http://l.top4top.io/m_2674cidkr0.mp3"
  },
  {
    "name": "JKT Jurus Rahasia Teleport",
    "url": "http://b.top4top.io/m_26744uimn0.mp3"
  },
  {
    "name": "JKT Jiwaru Days",
    "url": "http://c.top4top.io/m_2674ens380.mp3"
  },
  {
    "name": "JKT Rapsodi",
    "url": "http://f.top4top.io/m_267438o000.mp3"
  },
  {
    "name": "Mana Tukang Indomie",
    "url": "http://l.top4top.io/m_2700vi0vg1.mp3"
  },
  {
    "name": "Domba Kuring",
    "url": "http://g.top4top.io/m_2701l6zmn0.mp3"
  },
  {
    "name": "DJ campuran viral tiktok",
    "url": "http://e.top4top.io/m_2559yp1et0.mp3"
  },
  {
    "name": "Lagu Demo",
    "url": "http://i.top4top.io/m_2740vmsky0.mp3"
  },
  {
    "name": "Komang",
    "url": "http://k.top4top.io/m_27407eju90.mp3"
  },
  {
    "name": "Monokrom",
    "url": "http://c.top4top.io/m_2740ta77l0.mp3"
  },
  {
    "name": "Resah Jadi Luka",
    "url": "http://f.top4top.io/m_2740y9ni10.mp3"
  },
  {
    "name": "See you Again",
    "url": "http://e.top4top.io/m_2740v0jxu0.mp3"
  },
  {
    "name": "Not You",
    "url": "http://i.top4top.io/m_274067b4f0.mp3"
  },
  {
    "name": "Rungkad Versi Jepang",
    "url": "http://e.top4top.io/m_2740ik7le0.mp3"
  },
  {
    "name": "Mockingbird",
    "url": "http://f.top4top.io/m_273701fwu0.mp3"
  },
  {
    "name": "Di Sayidan regge",
    "url": "http://k.top4top.io/m_27375p3ur0.mp3"
  },
  {
    "name": "Kerasnya Kota",
    "url": "http://d.top4top.io/m_2737tppwc0.mp3"
  },
  {
    "name": "Dulu",
    "url": "http://h.top4top.io/m_274095e6q0.mp3"
  },
  {
    "name": "Dj Kamu Kolong koling",
    "url": "http://f.top4top.io/m_2740wkbzc0.mp3"
  },
  {
    "name": "Rosoh Bali",
    "url": "http://l.top4top.io/m_2740tzxac0.mp3"
  },
  {
    "name": "aku yg malang",
    "url": "http://i.top4top.io/m_27406s13n0.mp3"
  },
  {
    "name": "Ya sudahlah",
    "url": "http://f.top4top.io/m_2740b8axh0.mp3"
  },
  {
    "name": "Tak pernah ternilai",
    "url": "http://b.top4top.io/m_274029c410.mp3"
  },
  {
    "name": "selamat jalan kawan",
    "url": "http://k.top4top.io/m_2740f2b000.mp3"
  },
  {
    "name": "Jadilah Legenda",
    "url": "http://j.top4top.io/m_2740ho26w0.mp3"
  },
  {
    "name": "Anak Singkong",
    "url": "http://f.top4top.io/m_2740obtcg0.mp3"
  },
  {
    "name": "Dear god Versi Indo",
    "url": "http://h.top4top.io/m_2740bp3mg0.mp3"
  },
  {
    "name": "Ku tak bisa",
    "url": "http://c.top4top.io/m_2746jsj870.mp3"
  },
  {
    "name": "Dj Aitakata",
    "url": "http://e.top4top.io/m_2746cuna91.mp3"
  },
  {
    "name": "OT Persija",
    "url": "http://k.top4top.io/m_2746op2q73.mp3"
  },
  {
    "name": "Tinggal Kenangan",
    "url": "http://h.top4top.io/m_2746m081r2.mp3"
  },
  {
    "name": "skidi bom",
    "url": "http://d.top4top.io/m_282477dyn1.mp3"
  },
  {
    "name": "sprinter dave",
    "url": "http://h.top4top.io/m_28245ad8h1.mp3"
  },
  {
    "name": "susayang",
    "url": "http://c.top4top.io/m_2824q42961.mp3"
  },
  {
    "name": "jalan tengah",
    "url": "http://d.top4top.io/m_28242ssio1.mp3"
  },
  {
    "name": "nanti kita seperti ini",
    "url": "http://d.top4top.io/m_2824gbyh11.mp3"
  },
  {
    "name": "AGNEZ MO CIARA Get Loose",
    "url": "http://b.top4top.io/m_2824jmpqs1.mp3"
  },
  {
    "name": "Selamat tinggal Virgoun",
    "url": "http://c.top4top.io/m_282454bsv1.mp3"
  },
  {
    "name": "dawin make your speaker",
    "url": "http://k.top4top.io/m_2824idqo21.mp3"
  },
  {
    "name": "Khalid Young Dumb Broke",
    "url": "http://d.top4top.io/m_28244ls0c1.mp3"
  },
  {
    "name": "in start",
    "url": "http://c.top4top.io/m_2824e2znu1.mp3"
  },
  {
    "name": "alan walker not you",
    "url": "http://j.top4top.io/m_2824ggm3f1.mp3"
  },
  {
    "name": "Daun Jatuh Resah Jadi Luka",
    "url": "http://j.top4top.io/m_2824pdxar1.mp3"
  },
  {
    "name": "rumah singgah",
    "url": "http://c.top4top.io/m_2824hpc4n1.mp3"
  },
  {
    "name": "dj amroy",
    "url": "http://c.top4top.io/m_2824mqryy1.mp3"
  },
  {
    "name": "dj kuda poni",
    "url": "http://l.top4top.io/m_282433vgz1.mp3"
  },
  {
    "name": "dj cocok untuk santuy",
    "url": "http://i.top4top.io/m_2824qky781.mp3"
  },
  {
    "name": "playlist indo",
    "url": "http://l.top4top.io/m_287883cda1.mp3"
  },
  {
    "name": "walking back home",
    "url": "http://l.top4top.io/m_2878mh9d11.mp3"
  },
  {
    "name": "saat saat itu",
    "url": "http://j.top4top.io/m_2878fuxs51.mp3"
  },
  {
    "name": "sal pribadi",
    "url": "http://d.top4top.io/m_2879r8try2.mp3"
  },
  {
    "name": "Abadi",
    "url": "http://j.top4top.io/m_2879w9blf2.mp3"
  },
  {
    "name": "Hapus aku",
    "url": "http://l.top4top.io/m_2879odhsl1.mp3"
  },
  {
    "name": "Life goes on",
    "url": "http://k.top4top.io/m_28837im2h0.mp3"
  },
  {
    "name": "Changes",
    "url": "http://g.top4top.io/m_2883kw1gt0.mp3"
  },
  {
    "name": "Dear mama",
    "url": "http://b.top4top.io/m_28834z8w00.mp3"
  },
  {
    "name": "Pacs life",
    "url": "http://a.top4top.io/m_2883n409s0.mp3"
  },
  {
    "name": "Thugz Mansion",
    "url": "http://i.top4top.io/m_2883uyv850.mp3"
  },
  {
    "name": "All Eyez On Me",
    "url": "http://j.top4top.io/m_28837udml0.mp3"
  },
  {
    "name": "TABRAK MASUK",
    "url": "http://d.top4top.io/m_2880ecl4f0.mp3"
  },
  {
    "name": "Dream Shimizu Shota",
    "url": "http://d.top4top.io/m_2880s7jax2.mp3"
  },
  {
    "name": "It Will Rains",
    "url": "http://d.top4top.io/m_2881cay6c1.mp3"
  },
  {
    "name": "Flo Rida",
    "url": "http://j.top4top.io/m_2881b89xt1.mp3"
  },
  {
    "name": "Langit tak seharusnya biru",
    "url": "http://a.top4top.io/m_2904chaty0.mp3"
  },
  {
    "name": "Kau pemain utama",
    "url": "http://b.top4top.io/m_2904qkfcp0.mp3"
  },
  {
    "name": "Lovely",
    "url": "http://l.top4top.io/m_2716ygd490.mp3"
  },
  {
    "name": "Billie Elish Happier Than Ever",
    "url": "http://d.top4top.io/m_2713kuwa00.mp3"
  },
  {
    "name": "At My Worst",
    "url": "http://b.top4top.io/m_2713aaj1z0.mp3"
  },
  {
    "name": "Say You Wont Let Go",
    "url": "http://h.top4top.io/m_2713emejd0.mp3"
  },
  {
    "name": "Glorious",
    "url": "http://b.top4top.io/m_2716suook0.mp3"
  },
  {
    "name": "Febian Hingga Tua Bersama",
    "url": "http://e.top4top.io/m_2713sw4kq0.mp3"
  },
  {
    "name": "Last Child Saat Saat Itu",
    "url": "http://j.top4top.io/m_2713r4iqx0.mp3"
  },
  {
    "name": "Kaleb Its Only Me",
    "url": "http://c.top4top.io/m_2713kpsh20.mp3"
  },
  {
    "name": "Andmesh Andaikan Kau Datang",
    "url": "http://f.top4top.io/m_2713gjv970.mp3"
  },
  {
    "name": "Lonely",
    "url": "http://b.top4top.io/m_2567k0twk0.mp3"
  },
  {
    "name": "Heyek Crew Suwung",
    "url": "http://c.top4top.io/m_25671hko70.mp3"
  },
  {
    "name": "Bojo Galak",
    "url": "http://f.top4top.io/m_25695zdfe0.mp3"
  },
  {
    "name": "Take Me Home",
    "url": "http://a.top4top.io/m_26013d6730.mp3"
  },
  {
    "name": "Atlantis",
    "url": "http://e.top4top.io/m_2601hp5r10.mp3"
  },
  {
    "name": "SNAP",
    "url": "http://g.top4top.io/m_2601oi9aa0.mp3"
  },
  {
    "name": "One Direction",
    "url": "http://j.top4top.io/m_2601h1cty0.mp3"
  },
  {
    "name": "Proom Queen",
    "url": "http://d.top4top.io/m_2601vds8j0.mp3"
  },
  {
    "name": "December",
    "url": "http://j.top4top.io/m_2601twj6s0.mp3"
  },
  {
    "name": "Hindia Evaluasi",
    "url": "http://g.top4top.io/m_2601084lx0.mp3"
  },
  {
    "name": "Seandainya Vierra",
    "url": "http://g.top4top.io/m_2603nwiqz0.mp3"
  },
  {
    "name": "As It Was",
    "url": "http://k.top4top.io/m_2603mzl900.mp3"
  },
  {
    "name": "The Side Of Paradise",
    "url": "http://g.top4top.io/m_2603vzgb30.mp3"
  },
  {
    "name": "Somewhere Only We Know",
    "url": "http://e.top4top.io/m_2603i6lw10.mp3"
  },
  {
    "name": "DJ JOANA",
    "url": "http://c.top4top.io/m_2909c0o0b0.mp3"
  },
  {
    "name": "DJ OLD FF",
    "url": "http://b.top4top.io/m_29098efhg0.mp3"
  },
  {
    "name": "Jogja Istimewa",
    "url": "http://l.top4top.io/m_2603ikqcx0.mp3"
  },
  {
    "name": "Cintamu Sepahit Topi Miring",
    "url": "http://f.top4top.io/m_2585pzzvc0.mp3"
  },
  {
    "name": "Hujan ke marin",
    "url": "http://b.top4top.io/m_2625f4ghk0.mp3"
  },
  {
    "name": "DJ SHE DOESNT",
    "url": "http://l.top4top.io/m_2579374tg0.mp3"
  },
  {
    "name": "DJ MANTANKU DI POTONG POTONG",
    "url": "http://a.top4top.io/m_2579b74181.mp3"
  },
  {
    "name": "DJ DALINDA",
    "url": "http://b.top4top.io/m_2579f146p2.mp3"
  },
  {
    "name": "DJ INDUSTRY BABY",
    "url": "http://c.top4top.io/m_2579vjja73.mp3"
  },
  {
    "name": "ENAK BARU LAMA KAH",
    "url": "http://d.top4top.io/m_2579mat1h4.mp3"
  },
  {
    "name": "Keenan Te Scars",
    "url": "http://k.top4top.io/m_26097ubzo0.mp3"
  },
  {
    "name": "MUAK",
    "url": "http://c.top4top.io/m_2601ngkoe1.mp3"
  },
  {
    "name": "Nan ko paham",
    "url": "http://k.top4top.io/m_2888tpy261.mp3"
  },
  {
    "name": "See You Again",
    "url": "http://f.top4top.io/m_2888f21lb1.mp3"
  },
  {
    "name": "CINTAMU SEPAHIT TOPI MIRING",
    "url": "http://i.top4top.io/m_2610o0occ2.mp3"
  },
  {
    "name": "RIGTH NOW",
    "url": "http://b.top4top.io/m_2610rzp582.mp3"
  },
  {
    "name": "SUMMERTIME SADNESS",
    "url": "http://f.top4top.io/m_2610j02te0.mp3"
  },
  {
    "name": "ANOTHER LOVE",
    "url": "http://l.top4top.io/m_2610hbosg0.mp3"
  },
  {
    "name": "DEAR GOD",
    "url": "http://f.top4top.io/m_2610vubds0.mp3"
  },
  {
    "name": "DANDELIONS",
    "url": "http://e.top4top.io/m_2610r9ev40.mp3"
  },
  {
    "name": "THOSE EYES",
    "url": "http://k.top4top.io/m_2610vhz5v0.mp3"
  },
  {
    "name": "AFTER DARK",
    "url": "http://b.top4top.io/m_2610mi20v0.mp3"
  },
  {
    "name": "EVALUASI",
    "url": "http://i.top4top.io/m_2610bxxt80.mp3"
  },
  {
    "name": "HERE WITH ME",
    "url": "http://d.top4top.io/m_2610edcid0.mp3"
  },
  {
    "name": "RESAH JADI LUKA",
    "url": "http://g.top4top.io/m_2610tgziy0.mp3"
  },
  {
    "name": "VIVA LA VIDA",
    "url": "http://k.top4top.io/m_2610v8z3c0.mp3"
  },
  {
    "name": "BADUT",
    "url": "http://h.top4top.io/m_2610o8fae0.mp3"
  },
  {
    "name": "dia masalalu mu",
    "url": "http://l.top4top.io/m_2903ooz3f0.mp3"
  },
  {
    "name": "when i was your man",
    "url": "http://h.top4top.io/m_2903ckn2a0.mp3"
  },
  {
    "name": "it will rain",
    "url": "http://f.top4top.io/m_2903zhr1y0.mp3"
  },
  {
    "name": "dj malam pagi slowed",
    "url": "http://j.top4top.io/m_29037axg70.mp3"
  },
  {
    "name": "scott street",
    "url": "http://g.top4top.io/m_2903nbi5b0.mp3"
  },
  {
    "name": "escapism sped up",
    "url": "http://e.top4top.io/m_2903veqag0.mp3"
  },
  {
    "name": "stan dido",
    "url": "http://h.top4top.io/m_2903peavs0.mp3"
  },
  {
    "name": "heaven and back",
    "url": "http://e.top4top.io/m_2903uwz6m0.mp3"
  },
  {
    "name": "tak lagi samaa",
    "url": "http://e.top4top.io/m_290356ak10.mp3"
  },
  {
    "name": "rewrite the stars",
    "url": "http://f.top4top.io/m_25887dont9.mp3"
  },
  {
    "name": "bernafas tanpamu sped up",
    "url": "http://l.top4top.io/m_2903d23dq0.mp3"
  },
  {
    "name": "daddys home sped up",
    "url": "http://e.top4top.io/m_2903qjl2a0.mp3"
  },
  {
    "name": "last night on earth",
    "url": "http://j.top4top.io/m_2905wqk3m0.mp3"
  },
  {
    "name": "black and yellow",
    "url": "http://c.top4top.io/m_29053sqc30.mp3"
  },
  {
    "name": "one of the girls",
    "url": "http://l.top4top.io/m_29044yu831.mp3"
  },
  {
    "name": "if u could see me crying in my room",
    "url": "http://j.top4top.io/m_2907ak61q0.mp3"
  },
  {
    "name": "mask off",
    "url": "http://j.top4top.io/m_26342v5q80.mp3"
  },
  {
    "name": "tell em",
    "url": "http://f.top4top.io/m_2909t1nsb0.mp3"
  },
  {
    "name": "you know how we do it",
    "url": "http://k.top4top.io/m_2634t70700.mp3"
  },
  {
    "name": "snowman",
    "url": "http://k.top4top.io/m_2909qg1ta0.mp3"
  },
  {
    "name": "the night we met",
    "url": "http://h.top4top.io/m_2904r8sgb5.mp3"
  },
  {
    "name": "cant help falling in love",
    "url": "http://f.top4top.io/m_2904u8xjq3.mp3"
  },
  {
    "name": "glimpse of us",
    "url": "http://k.top4top.io/m_2911v8cjv4.mp3"
  },
  {
    "name": "my love mine all mine",
    "url": "http://g.top4top.io/m_2913qrwvr0.mp3"
  },
  {
    "name": "cupid",
    "url": "http://l.top4top.io/m_2914918mb0.mp3"
  },
  {
    "name": "someone to stay",
    "url": "http://h.top4top.io/m_28855e9yb0.mp3"
  },
  {
    "name": "falling like the stars",
    "url": "http://j.top4top.io/m_29143fnj80.mp3"
  },
  {
    "name": "just a friends to you",
    "url": "http://a.top4top.io/m_291452oqu0.mp3"
  },
  {
    "name": "tampar",
    "url": "http://j.top4top.io/m_2914httlt0.mp3"
  },
  {
    "name": "bohongi hati",
    "url": "http://h.top4top.io/m_29152dz3b0.mp3"
  },
  {
    "name": "country road take me home",
    "url": "http://c.top4top.io/m_2923f4iyi0.mp3"
  },
  {
    "name": "uptopia hujan",
    "url": "http://j.top4top.io/m_2925u27wp1.mp3"
  },
  {
    "name": "Sweet but physco x bad romance",
    "url": "http://f.top4top.io/m_2925m1s7t0.mp3"
  },
  {
    "name": "Jomblo happy speed up",
    "url": "http://a.top4top.io/m_2925w073k0.mp3"
  },
  {
    "name": "Heres is your perfect",
    "url": "http://i.top4top.io/m_2925wnftg0.mp3"
  },
  {
    "name": "Mendua speed up",
    "url": "http://h.top4top.io/m_292546jzd0.mp3"
  },
  {
    "name": "Dont let me down",
    "url": "http://h.top4top.io/m_2925cns760.mp3"
  },
  {
    "name": "It aint me",
    "url": "http://b.top4top.io/m_29257898v0.mp3"
  },
  {
    "name": "Daddys home",
    "url": "http://d.top4top.io/m_2925mvojr0.mp3"
  },
  {
    "name": "Happier",
    "url": "http://k.top4top.io/m_2925m0q4z0.mp3"
  },
  {
    "name": "Vegas slowed",
    "url": "http://d.top4top.io/m_292512mq20.mp3"
  },
  {
    "name": "DJ bring me to life",
    "url": "http://h.top4top.io/m_29253pyhh0.mp3"
  },
  {
    "name": "Derniere danse",
    "url": "http://b.top4top.io/m_2925q5gwr0.mp3"
  },
  {
    "name": "Habits",
    "url": "http://b.top4top.io/m_29252gpri0.mp3"
  },
  {
    "name": "Drunk text speed up",
    "url": "http://g.top4top.io/m_29243o0ad0.mp3"
  },
  {
    "name": "Doin time",
    "url": "http://g.top4top.io/m_2924hu9wt0.mp3"
  },
  {
    "name": "Trapped In my mind",
    "url": "http://e.top4top.io/m_2924wa6ln0.mp3"
  },
  {
    "name": "Karena Kamu Geisha",
    "url": "http://d.top4top.io/m_29761z5no1.mp3"
  },
  {
    "name": "Resah jadi luka Daun jatuh",
    "url": "http://e.top4top.io/m_2976wlwr02.mp3"
  },
  {
    "name": "DUKA Last Child",
    "url": "http://f.top4top.io/m_2976xfr163.mp3"
  },
  {
    "name": "Lampu Merah The Lantis",
    "url": "http://g.top4top.io/m_29767wah54.mp3"
  },
  {
    "name": "Last Child Sekuat Hatimu",
    "url": "http://h.top4top.io/m_2976564yt5.mp3"
  },
  {
    "name": "Last Child Diary Depresiku",
    "url": "http://i.top4top.io/m_2976sk5iy6.mp3"
  },
  {
    "name": "Last Child Seluruh Nafas Ini",
    "url": "http://j.top4top.io/m_29762si8i7.mp3"
  },
  {
    "name": "Andra and The Backbone Sempurna",
    "url": "http://k.top4top.io/m_2976ygc528.mp3"
  },
  {
    "name": "Virgoun Ft Audy Selamat tinggal",
    "url": "http://l.top4top.io/m_2976j8ot69.mp3"
  },
  {
    "name": "Armada Asal kau bahagia",
    "url": "http://a.top4top.io/m_29765gy3610.mp3"
  },
  {
    "name": "Lexnour Its to late",
    "url": "http://k.top4top.io/m_3058c64o40.mp3"
  },
  {
    "name": "Lexnour Say goodbye",
    "url": "http://e.top4top.io/m_3058y2lft0.mp3"
  },
  {
    "name": "Lexnour My depression",
    "url": "http://b.top4top.io/m_3058pbtnt0.mp3"
  },
  {
    "name": "Lexnour I hate you now",
    "url": "http://f.top4top.io/m_30585mblr0.mp3"
  },
  {
    "name": "Lexnour Memories of you",
    "url": "http://j.top4top.io/m_3058hzsz10.mp3"
  },
  {
    "name": "Lexnour Believe it",
    "url": "http://b.top4top.io/m_3058x07gd0.mp3"
  },
  {
    "name": "Lexnour Got me stuck",
    "url": "http://f.top4top.io/m_3058r3sdv0.mp3"
  },
  {
    "name": "Lexnour The lonely song",
    "url": "http://h.top4top.io/m_3058dvoat0.mp3"
  },
  {
    "name": "Lexnour Better me",
    "url": "http://l.top4top.io/m_3058r1n7l0.mp3"
  },
  {
    "name": "Lexnour Ride or die",
    "url": "http://a.top4top.io/m_3058j678q0.mp3"
  },
  {
    "name": "Taxi hujan kemarin",
    "url": "http://k.top4top.io/m_30589ofqr0.mp3"
  },
  {
    "name": "Rasa ini",
    "url": "http://d.top4top.io/m_3058vzzqt0.mp3"
  },
  {
    "name": "Lumpuhkanlah Ingatanku",
    "url": "http://f.top4top.io/m_3058qqb6t0.mp3"
  },
  {
    "name": "Ruang Rindu Letto",
    "url": "http://i.top4top.io/m_3058f2h1n0.mp3"
  },
  {
    "name": "Daddys Home",
    "url": "http://e.top4top.io/m_29568v59t1.mp3"
  },
  {
    "name": "Starboy",
    "url": "http://f.top4top.io/m_29564dgmv2.mp3"
  },
  {
    "name": "Taylor Swift Cruel Summer",
    "url": "http://g.top4top.io/m_2956bnph23.mp3"
  },
  {
    "name": "Taylor Swift Style",
    "url": "http://h.top4top.io/m_2956y8xqp4.mp3"
  },
  {
    "name": "Jungkook Seven",
    "url": "http://j.top4top.io/m_2956oxx246.mp3"
  },
  {
    "name": "Keshi Limbo",
    "url": "http://k.top4top.io/m_2956tqqj77.mp3"
  },
  {
    "name": "Yuji Old Love",
    "url": "http://l.top4top.io/m_29568sf6b8.mp3"
  },
  {
    "name": "I Wanna Be Yours",
    "url": "http://a.top4top.io/m_2956n0ibe9.mp3"
  },
  {
    "name": "Beauty And The Beat",
    "url": "http://b.top4top.io/m_2956xcae810.mp3"
  },
  {
    "name": "Dandelions",
    "url": "http://e.top4top.io/m_295610k261.mp3"
  },
  {
    "name": "Dhruv Double Take",
    "url": "http://f.top4top.io/m_29567xs482.mp3"
  },
  {
    "name": "Melting",
    "url": "http://g.top4top.io/m_2956zyyli3.mp3"
  },
  {
    "name": "Taylor Swift Lover",
    "url": "http://i.top4top.io/m_2956lrv7y4.mp3"
  },
  {
    "name": "Still With You",
    "url": "http://j.top4top.io/m_29561nxvb5.mp3"
  },
  {
    "name": "Somebody Pleasure",
    "url": "http://k.top4top.io/m_29560c0sp6.mp3"
  },
  {
    "name": "Cheating On You",
    "url": "http://l.top4top.io/m_2956vkrs77.mp3"
  },
  {
    "name": "One Of The Girls",
    "url": "http://a.top4top.io/m_2956uyq468.mp3"
  },
  {
    "name": "Pesan Terakhir",
    "url": "http://b.top4top.io/m_29569htfz9.mp3"
  },
  {
    "name": "Terlukis Indah",
    "url": "http://c.top4top.io/m_29569rb7r10.mp3"
  },
  {
    "name": "Haunt U Lil Peep",
    "url": "http://k.top4top.io/m_3176bdgir0.mp3"
  },
  {
    "name": "One More Light Linkin Park",
    "url": "http://l.top4top.io/m_31760d37w1.mp3"
  },
  {
    "name": "Youre Somebody Else",
    "url": "http://c.top4top.io/m_3176mpcek4.mp3"
  },
  {
    "name": "Love The Way You Lie",
    "url": "http://b.top4top.io/m_3176mhu2a3.mp3"
  },
  {
    "name": "Serena For Revenge",
    "url": "http://e.top4top.io/m_3175d3unb0.mp3"
  },
  {
    "name": "Resah Jadi Luka",
    "url": "http://l.top4top.io/m_25549tgt90.mp3"
  },
  {
    "name": "Closed Door",
    "url": "http://b.top4top.io/m_2968a03es0.mp3"
  },
  {
    "name": "Take That",
    "url": "http://c.top4top.io/m_3087drteo0.mp3"
  },
  {
    "name": "December",
    "url": "http://g.top4top.io/m_3134yjhr10.mp3"
  },
  {
    "name": "Blue Wednesday",
    "url": "http://c.top4top.io/m_3175etp401.mp3"
  },
  {
    "name": "We Dont Talk",
    "url": "http://e.top4top.io/m_3100oa69r0.mp3"
  },
  {
    "name": "Stereo Love",
    "url": "http://h.top4top.io/m_3159nnlth0.mp3"
  },
  {
    "name": "DJ Joana",
    "url": "http://h.top4top.io/m_3176kmnop0.mp3"
  },
  {
    "name": "DJ On The Floor",
    "url": "http://a.top4top.io/m_3176gxlto2.mp3"
  },
  {
    "name": "Danza Kuduro",
    "url": "http://i.top4top.io/m_3176u6wua1.mp3"
  },
  {
    "name": "Sweet Love",
    "url": "http://k.top4top.io/m_3176zhxig3.mp3"
  },
  {
    "name": "Dola Dola",
    "url": "http://f.top4top.io/m_3100isui91.mp3"
  },
  {
    "name": "We Dont Talk",
    "url": "http://e.top4top.io/m_3100oa69r0.mp3"
  },
  {
    "name": "Fireflies",
    "url": "http://g.top4top.io/m_3099yxeso0.mp3"
  },
  {
    "name": "Wide Awake",
    "url": "http://h.top4top.io/m_30996ckam1.mp3"
  },
  {
    "name": "Heat Waves",
    "url": "http://c.top4top.io/m_3099bkss80.mp3"
  },
  {
    "name": "Separuh Aku",
    "url": "http://d.top4top.io/m_3099tvlpg1.mp3"
  },
  {
    "name": "Feast Demi Peradaban",
    "url": "http://l.top4top.io/m_3084lrf001.mp3"
  },
  {
    "name": "Baon Cikadap",
    "url": "http://l.top4top.io/m_2831o1wpv0.mp3"
  },
  {
    "name": "This is Cogil",
    "url": "http://g.top4top.io/m_2973b3msv6.mp3"
  },
  {
    "name": "Daddys Home",
    "url": "http://k.top4top.io/m_2965jll2f3.mp3"
  },
  {
    "name": "Diamond in the Sky",
    "url": "http://g.top4top.io/m_2962j4wki0.mp3"
  },
  {
    "name": "Maulana Ramadhan",
    "url": "http://k.top4top.io/m_2966sg16w0.mp3"
  },
  {
    "name": "Hilang Harapan",
    "url": "http://l.top4top.io/m_3095vk9i40.mp3"
  },
  {
    "name": "I Found You",
    "url": "http://h.top4top.io/m_3182ivy9d0.mp3"
  },
  {
    "name": "Terek Bale",
    "url": "http://e.top4top.io/m_3177m9sei0.mp3"
  },
  {
    "name": "Try Again",
    "url": "http://b.top4top.io/m_29569htfz9.mp3"
  },
  {
    "name": "Saturn",
    "url": "http://h.top4top.io/m_3020vso6p0.mp3"
  },
  {
    "name": "Est Ce que tu maimes",
    "url": "http://h.top4top.io/m_3141gbk0z0.mp3"
  },
  {
    "name": "Take Me Home",
    "url": "http://i.top4top.io/m_3170iui8h0.mp3"
  },
  {
    "name": "Mortals",
    "url": "http://l.top4top.io/m_3172jd7fc0.mp3"
  },
  {
    "name": "Oasis Wonderwall",
    "url": "http://d.top4top.io/m_3209kc7kv1.mp3"
  },
  {
    "name": "Oasis Dont Look Back In Anger",
    "url": "http://e.top4top.io/m_3209zchvu2.mp3"
  },
  {
    "name": "Oasis Stop Crying Your Heart Out",
    "url": "http://f.top4top.io/m_3209nanw83.mp3"
  },
  {
    "name": "Oasis Live Forever",
    "url": "http://g.top4top.io/m_3209oemvz4.mp3"
  },
  {
    "name": "Oasis Stand By Me",
    "url": "http://h.top4top.io/m_32090vi695.mp3"
  },
  {
    "name": "Ransom x Juice WRLD",
    "url": "http://i.top4top.io/m_32356sbap0.mp3"
  },
  {
    "name": "Fuck Love",
    "url": "http://l.top4top.io/m_32402lkjm0.mp3"
  },
  {
    "name": "Hope",
    "url": "http://i.top4top.io/m_3240n2oni0.mp3"
  },
  {
    "name": "All girls are the same",
    "url": "http://i.top4top.io/m_324091rql0.mp3"
  },
  {
    "name": "Lucid dreams",
    "url": "http://l.top4top.io/m_3240pl5wx0.mp3"
  },
  {
    "name": "Knock knock",
    "url": "http://g.top4top.io/m_3242rqv0w0.mp3"
  },
  {
    "name": "Shotta flow",
    "url": "http://d.top4top.io/m_3242e0avm0.mp3"
  },
  {
    "name": "Gang unit",
    "url": "http://h.top4top.io/m_32429v4ne0.mp3"
  },
  {
    "name": "They not like us",
    "url": "http://e.top4top.io/m_3242qjp0i0.mp3"
  },
  {
    "name": "Everybody dies in their nightmare",
    "url": "http://g.top4top.io/m_3244vtbb70.mp3"
  },
  {
    "name": "Revenge",
    "url": "http://h.top4top.io/m_3247x5hub0.mp3"
  },
  {
    "name": "Moonlight",
    "url": "http://c.top4top.io/m_3247hi39p0.mp3"
  },
  {
    "name": "Bandit",
    "url": "http://e.top4top.io/m_3247xdvwn0.mp3"
  },
  {
    "name": "Robbery",
    "url": "http://j.top4top.io/m_3247lo84g0.mp3"
  },
  {
    "name": "Lean wit me",
    "url": "http://a.top4top.io/m_32479qta30.mp3"
  },
  {
    "name": "Bad",
    "url": "http://d.top4top.io/m_3247atrxf0.mp3"
  },
  {
    "name": "Look at me",
    "url": "http://j.top4top.io/m_3247w4wfl0.mp3"
  },
  {
    "name": "TLC",
    "url": "http://c.top4top.io/m_31183ivvx1.mp3"
  },
  {
    "name": "Armed n dangerous",
    "url": "http://a.top4top.io/m_3261swg5n0.mp3"
  },
  {
    "name": "Wasted",
    "url": "http://i.top4top.io/m_3261d3nw90.mp3"
  },
  {
    "name": "Legends",
    "url": "http://l.top4top.io/m_3261f25tx0.mp3"
  },
  {
    "name": "Empty out your pocket",
    "url": "http://b.top4top.io/m_3261lmxf10.mp3"
  },
  {
    "name": "Took her to",
    "url": "http://j.top4top.io/m_32648u1p70.mp3"
  },
  {
    "name": "Suicidal Juice x YNW Melly",
    "url": "http://a.top4top.io/m_3264bokoh0.mp3"
  },
  {
    "name": "Murder on my mind",
    "url": "http://e.top4top.io/m_3269jh7i00.mp3"
  },
  {
    "name": "Stay high",
    "url": "http://i.top4top.io/m_3273ehnvq0.mp3"
  },
  {
    "name": "Black n white",
    "url": "http://i.top4top.io/m_3273oo07u0.mp3"
  },
  {
    "name": "Wishing well",
    "url": "http://b.top4top.io/m_3273cssg60.mp3"
  },
  {
    "name": "Pills in the regal",
    "url": "http://g.top4top.io/m_3273sooc80.mp3"
  },
  {
    "name": "Smile",
    "url": "http://l.top4top.io/m_3273ucufg0.mp3"
  },
  {
    "name": "Crazy Story",
    "url": "http://b.top4top.io/m_3273tdyn00.mp3"
  },
  {
    "name": "No Flaws",
    "url": "http://g.top4top.io/m_3273x0ntg0.mp3"
  },
  {
    "name": "Kumpulan DJ Link StreamZeno",
    "url": "http://stream.zeno.fm/iitnog3filatv.mp3"
  },
  {
    "name": "Kumpulan drill Remix",
    "url": "http://stream.zeno.fm/8zv9jj3rnxmvv.mp3"
  },
  {
    "name": "is somebody gonna match",
    "url": "http://c.top4top.io/m_3279j0k901.mp3"
  },
  {
    "name": "ceilings",
    "url": "http://g.top4top.io/m_3387w9bh82.mp3"
  },
  {
    "name": "fade into you",
    "url": "http://h.top4top.io/m_3387eshbv3.mp3"
  },
  {
    "name": "instrumental",
    "url": "http://i.top4top.io/m_33873hegm4.mp3"
  },
  {
    "name": "middle of nowhere",
    "url": "http://j.top4top.io/m_338747nmd5.mp3"
  },
  {
    "name": "mrs magic",
    "url": "http://k.top4top.io/m_3387e2bds6.mp3"
  },
  {
    "name": "myth",
    "url": "http://l.top4top.io/m_3387k5ye17.mp3"
  },
  {
    "name": "pay no mind",
    "url": "http://a.top4top.io/m_33872h5vx8.mp3"
  },
  {
    "name": "sailor song",
    "url": "http://b.top4top.io/m_3387rnb8r9.mp3"
  },
  {
    "name": "the message",
    "url": "http://c.top4top.io/m_3387drcmr10.mp3"
  },
  {
    "name": "Dj tetus nona",
    "url": "http://g.top4top.io/m_33903hp350.mp3"
  },
  {
    "name": "Dj stecu",
    "url": "http://e.top4top.io/m_339099viw2.mp3"
  },
  {
    "name": "Dj teropet",
    "url": "http://l.top4top.io/m_3390izzwk3.mp3"
  },
  {
    "name": "Kenangan terindah",
    "url": "http://j.top4top.io/m_3390unxce7.mp3"
  },
  {
    "name": "Kenangan",
    "url": "http://d.top4top.io/m_3391dlzmj9.mp3"
  },
  {
    "name": "Tresno lianee",
    "url": "http://k.top4top.io/m_3414xmt8j0.mp3"
  },
  {
    "name": "Indo rep",
    "url": "http://l.top4top.io/m_34145hm7v0.mp3"
  },
  {
    "name": "Mangu",
    "url": "http://k.top4top.io/m_3418ocbpu0.mp3"
  },
  {
    "name": "lagu galau",
    "url": "http://f.top4top.io/m_3431jbl9x0.mp3"
  },
  {
    "name": "komang versi cewe",
    "url": "http://k.top4top.io/m_3431u4ls90.mp3"
  },
  {
    "name": "Artic Monkey full album",
    "url": "http://h.top4top.io/m_3434oiuws1.mp3"
  },
  {
    "name": "Topeng monyet",
    "url": "http://d.top4top.io/m_343559z0w1.mp3"
  },
  {
    "name": "POU SATU JAM SAMPE TEPAR",
    "url": "http://e.top4top.io/m_343616ssc1.mp3"
  },
  {
    "name": "Teman Sejati",
    "url": "http://e.top4top.io/m_34377pvb20.mp3"
  },
  {
    "name": "lil tatang arivena",
    "url": "http://d.top4top.io/m_3438pugbg0.mp3"
  },
  {
    "name": "login gta r",
    "url": "http://d.top4top.io/m_3438o8ws40.mp3"
  },
  {
    "name": "mesin tempur",
    "url": "http://youtu.be/ffHjn0IT9WA?si=pIFr89bNHiBc3_e7.mp3"
  }
]
 